Cargo.toml
LICENSE
MANIFEST.in
README.md
README_Python.md
pyproject.toml
setup.cfg
setup.py
python/seuif97/__init__.py
python/seuif97.egg-info/PKG-INFO
python/seuif97.egg-info/SOURCES.txt
python/seuif97.egg-info/dependency_links.txt
python/seuif97.egg-info/not-zip-safe
python/seuif97.egg-info/top_level.txt
src/cdecl_c_if97.rs
src/lib.rs
src/python_if97.rs
src/rust_if97.rs
src/stdcall_c_if97.rs
src/algo/mod.rs
src/algo/polynomial.rs
src/algo/polynomial_steps.rs
src/algo/root.rs
src/common/boundaries.rs
src/common/constant.rs
src/common/mod.rs
src/common/propertry_id.rs
src/common/propertry_pairs.rs
src/common/region.rs
src/common/transport_further.rs
src/r1/mod.rs
src/r1/region1.rs
src/r1/region1_T_phps.rs
src/r1/region1_gfe.rs
src/r1/region1_pT.rs
src/r1/region1_pT_ext.rs
src/r1/region1_p_hs.rs
src/r1/region1_pair_ext.rs
src/r2/mod.rs
src/r2/region2.rs
src/r2/region2_T_ph.rs
src/r2/region2_T_ps.rs
src/r2/region2_gfe.rs
src/r2/region2_pT.rs
src/r2/region2_pT_ext.rs
src/r2/region2_p_hs.rs
src/r2/region2_pair_ext.rs
src/r3/mod.rs
src/r3/region3.rs
src/r3/region3_Td.rs
src/r3/region3_Td_ext.rs
src/r3/region3_Tv_phps.rs
src/r3/region3_hfe.rs
src/r3/region3_p_hs.rs
src/r3/region3_pair_ext.rs
src/r3/region3_v_pT.rs
src/r3/region3_v_subregion_pT.rs
src/r4/mod.rs
src/r4/region4.rs
src/r4/region4_T_hs.rs
src/r4/region4_pTx.rs
src/r4/region4_pair_ext.rs
src/r4/region4_sat_pT.rs
src/r5/mod.rs
src/r5/region5.rs
src/r5/region5_gfe.rs
src/r5/region5_pT.rs
src/r5/region5_pT_ext.rs
src/r5/region5_pair_ext.rs
src/r5/region5_ph_ps_hs.rs