Metadata-Version: 2.1
Name: seuif97
Version: 2.2.0
Summary: The Python API of the high-speed IAPWS-IF97 package in Rust
Home-page: https://github.com/thermalogic/RustSEUIF97
Author: Cheng Maohua
Author-email: cmh@seu.edu.cn
License: MIT
Keywords: IAPWS-IF97,IF97
Classifier: Programming Language :: Python :: 3
Classifier: Topic :: Scientific/Engineering
Requires-Python: >=3.0
License-File: LICENSE
